LICENSE
README.md
setup.cfg
setup.py
asgardeo_auth/__init__.py
asgardeo_auth/_helpers.py
asgardeo_auth/app_consts.py
asgardeo_auth/asgardeo_auth.py
asgardeo_auth/framework.py
asgardeo_auth/oidc_flow.py
asgardeo_auth/pkce.py
asgardeo_auth/Integration/__init__.py
asgardeo_auth/Integration/flask_client/__init__.py
asgardeo_auth/Integration/flask_client/flask_asgardeo_auth.py
asgardeo_auth/Integration/flask_client/framework.py
asgardeo_auth/common/__init__.py
asgardeo_auth/common/security.py
asgardeo_auth/constants/__init__.py
asgardeo_auth/constants/common.py
asgardeo_auth/constants/endpoints.py
asgardeo_auth/constants/token.py
asgardeo_auth/constants/user.py
asgardeo_auth/exception/__init__.py
asgardeo_auth/exception/asgardeo_auth_error.py
asgardeo_auth/models/__init__.py
asgardeo_auth/models/auth_config.py
asgardeo_auth/models/authenticated_user.py
asgardeo_auth/models/crypto.py
asgardeo_auth/models/op_Configuration.py
asgardeo_auth/models/token_response.py
asgardeo_auth_python_sdk.egg-info/PKG-INFO
asgardeo_auth_python_sdk.egg-info/SOURCES.txt
asgardeo_auth_python_sdk.egg-info/dependency_links.txt
asgardeo_auth_python_sdk.egg-info/requires.txt
asgardeo_auth_python_sdk.egg-info/top_level.txt